c2sketch/__init__.py
c2sketch/app/__init__.py
c2sketch/app/config.py
c2sketch/app/data/__init__.py
c2sketch/app/data/execution.py
c2sketch/app/data/models.py
c2sketch/app/edit.py
c2sketch/app/execute/__init__.py
c2sketch/app/execute/_shared.py
c2sketch/app/execute/actors.py
c2sketch/app/execute/displays.py
c2sketch/app/execute/manage.py
c2sketch/app/model/__init__.py
c2sketch/app/model/manage.py
c2sketch/app/model/nodes/__init__.py
c2sketch/app/model/nodes/actor.py
c2sketch/app/model/nodes/information_space.py
c2sketch/app/model/nodes/location.py
c2sketch/app/model/nodes/model.py
c2sketch/app/model/nodes/record_type.py
c2sketch/app/model/nodes/task.py
c2sketch/app/model/nodes/task_definition.py
c2sketch/app/model/nodes/task_instance.py
c2sketch/app/model/structure.py
c2sketch/app/patterns.py
c2sketch/app/plugins.py
c2sketch/app/standalone.py
c2sketch/app/static/__init__.py
c2sketch/app/static/c2s-logo.png
c2sketch/app/static/c2s_editor.js
c2sketch/app/static/c2s_mode.js
c2sketch/app/static/c2sketch.css
c2sketch/app/static/resizer.js
c2sketch/app/static/svg-canvas.js
c2sketch/app/ui.py
c2sketch/check/__init__.py
c2sketch/check/constraints.py
c2sketch/check/references.py
c2sketch/cli.py
c2sketch/execute/__init__.py
c2sketch/execute/plugins.py
c2sketch/execute/state.py
c2sketch/export/__init__.py
c2sketch/export/excel.py
c2sketch/export/networkx.py
c2sketch/export/reports.py
c2sketch/models/__init__.py
c2sketch/models/collection.py
c2sketch/models/execution.py
c2sketch/models/identifier.py
c2sketch/models/inference.py
c2sketch/models/structure.py
c2sketch/plugins/data_table.py
c2sketch/plugins/data_transfer.py
c2sketch/plugins/map_plot.py
c2sketch/plugins/timer.py
c2sketch/read/__init__.py
c2sketch/read/folder.py
c2sketch/read/model.py
c2sketch/read/scenario.py
c2sketch/visualizations/__init__.py
c2sketch/visualizations/actor_locations.py
c2sketch/visualizations/color_util.py
c2sketch/visualizations/information_flow.py
c2sketch/visualizations/org_chart.py
c2sketch-0.3.2.dist-info/LICENCE
c2sketch-0.3.2.dist-info/METADATA
c2sketch-0.3.2.dist-info/WHEEL
c2sketch-0.3.2.dist-info/entry_points.txt
c2sketch-0.3.2.dist-info/RECORD
